aipdf/__init__.py
aipdf/ocr.py
aipdf-0.0.7.0.dist-info/licenses/LICENSE
aipdf-0.0.7.0.dist-info/METADATA
aipdf-0.0.7.0.dist-info/WHEEL
aipdf-0.0.7.0.dist-info/top_level.txt
aipdf-0.0.7.0.dist-info/RECORD
