Metadata-Version: 2.4
Name: aipdf
Version: 0.0.7.0
Summary: A tool to extract PDF files to markdown, or any other format using AI
Author-email: Jorge Torres <support@mindsdb.com>
License: MIT
Project-URL: Homepage, https://github.com/mindsdb/aipdf
Project-URL: Repository, https://github.com/mindsdb/aipdf.git
Keywords: pdf,markdown,ai,conversion,openai
Classifier: Programming Language :: Python :: 3
Classifier: License :: OSI Approved :: MIT License
Classifier: Operating System :: OS Independent
Requires-Python: >=3.7
License-File: LICENSE
Requires-Dist: PyMuPDF==1.25.2
Requires-Dist: openai<3.0.0,>=2.0.0
Dynamic: license-file
